burger/__init__.py
burger/_find_visual_studio.py
burger/_find_win_sdks.py
burger/_vsinstance.py
burger/buildutils.py
burger/cleanutils.py
burger/fileutils.py
burger/git.py
burger/locators.py
burger/perforce.py
burger/setuputils.py
burger/strutils.py
burger/validators.py
burger/windowsutils.py
burger/xcode.py
burger-1.5.1.dist-info/licenses/LICENSE.txt
burger-1.5.1.dist-info/METADATA
burger-1.5.1.dist-info/WHEEL
burger-1.5.1.dist-info/top_level.txt
burger-1.5.1.dist-info/RECORD
